mantis/__init__.py
mantis/adapters/__init__.py
mantis/adapters/diff_adapter.py
mantis/adapters/projector.py
mantis/adapters/var_selector.py
mantis/architecture/__init__.py
mantis/architecture/architecture.py
mantis/architecture/tokgen_utils/__init__.py
mantis/architecture/tokgen_utils/convolution.py
mantis/architecture/tokgen_utils/encoders.py
mantis/architecture/vit_utils/__init__.py
mantis/architecture/vit_utils/positional_encoding.py
mantis/architecture/vit_utils/transformer.py
mantis/trainer/__init__.py
mantis/trainer/trainer.py
mantis/trainer/trainer_utils/__init__.py
mantis/trainer/trainer_utils/architecture.py
mantis/trainer/trainer_utils/augmentation.py
mantis/trainer/trainer_utils/criterion.py
mantis/trainer/trainer_utils/dataset.py
mantis/trainer/trainer_utils/scheduling.py
mantis_tsfm-0.2.0.dist-info/LICENSE
mantis_tsfm-0.2.0.dist-info/METADATA
mantis_tsfm-0.2.0.dist-info/WHEEL
mantis_tsfm-0.2.0.dist-info/RECORD
