Metadata-Version: 2.1
Name: mantis-tsfm
Version: 0.2.0
Summary: Mantis: Lightweight Calibrated Foundation Model for User-Friendly Time Series Classification
License: MIT
Keywords: Time Series Foundation Model,Classification,Transformer
Author: Vasilii Feofanov
Author-email: vasilii.feofanov@huawei.com
Maintainer: Vasilii Feofanov
Maintainer-email: vasilii.feofanov@huawei.com
Requires-Python: >=3.9,<4.0
Classifier: Intended Audience :: Developers
Classifier: Intended Audience :: Science/Research
Classifier: License :: OSI Approved :: MIT License
Classifier: Programming Language :: Python :: 3
Classifier: Programming Language :: Python :: 3.9
Classifier: Programming Language :: Python :: 3.10
Classifier: Programming Language :: Python :: 3.11
Classifier: Programming Language :: Python :: 3.12
Classifier: Programming Language :: Python :: 3.13
Classifier: Topic :: Scientific/Engineering :: Artificial Intelligence
Requires-Dist: einops (>=0.8,<0.9)
Requires-Dist: huggingface-hub (>=0.23,<0.24)
Requires-Dist: numpy (>=1.23,<3.0)
Requires-Dist: pandas (>=1.5,<3.0)
Requires-Dist: safetensors (>=0.4,<0.5)
Requires-Dist: scikit-learn (>=1.2,<2.0)
Requires-Dist: torch (>=1.12,<3.0)
Requires-Dist: tqdm (>=4.64,<5.0)
